envorm/__init__.py
envorm-0.0.6.dist-info/LICENSE
envorm-0.0.6.dist-info/METADATA
envorm-0.0.6.dist-info/WHEEL
envorm-0.0.6.dist-info/top_level.txt
envorm-0.0.6.dist-info/RECORD
