Metadata-Version: 2.1
Name: envorm
Version: 0.0.6
Summary: An ORM-like interface for environment variables.
Home-page: https://github.com/winkidney/envorm
Author: UNKNOWN
Author-email: UNKNOWN
License: MIT
Platform: UNKNOWN
